[
    {
        "id": "1",
        "Name": "Golden Gupta",
        "Branch": "BCA",
        "Uni-Roll": "2200328",
        "Class-Roll": "226618"
    },
    {
        "id": "2",
        "Name": "Golden Gupta",
        "Branch": "BCA",
        "Uni-Roll": "2200328",
        "Class-Roll": "226618"
    },
    {
        "id": "3",
        "Name": "Golden Gupta",
        "Branch": "BCA",
        "Uni-Roll": "2200328",
        "Class-Roll": "226618"
    },
    {
        "id": "4",
        "Name": "Golden Gupta",
        "Branch": "BCA",
        "Uni-Roll": "2200328",
        "Class-Roll": "226618"
    },
    {
        "id": "5",
        "Name": "Golden Gupta",
        "Branch": "BCA",
        "Uni-Roll": "2200328",
        "Class-Roll": "226618"
    },
    {
        "id": "6",
        "Name": "Golden Gupta",
        "Branch": "BCA",
        "Uni-Roll": "2200328",
        "Class-Roll": "226618"
    }
]